{
  "AgendaContribute.Canvas.fromAgenda": [
    {
      "type": 0,
      "value": "from the agenda"
    }
  ],
  "AgendaContribute.Canvas.shareEvent": [
    {
      "type": 0,
      "value": "Share an event"
    }
  ],
  "AgendaContribute.Canvas.takeEvent": [
    {
      "type": 0,
      "value": "Take"
    }
  ],
  "AgendaContribute.Canvas.toAgenda": [
    {
      "type": 0,
      "value": "to the agenda"
    }
  ],
  "AgendaContribute.CanvasWithStepper.addEvent": [
    {
      "type": 0,
      "value": "Ajouter un événement"
    }
  ],
  "AgendaContribute.CanvasWithStepper.editDraftTitle": [
    {
      "type": 0,
      "value": "Draft"
    }
  ],
  "AgendaContribute.ClosedMessage.forAdminModerators": [
    {
      "type": 0,
      "value": "This agenda is currently not open to contributors. Only administrators or moderators can add events."
    }
  ],
  "AgendaContribute.ClosedMessage.forContributors": [
    {
      "type": 0,
      "value": "This agenda is not or no longer open for new contributions."
    }
  ],
  "AgendaContribute.EventEdit.update": [
    {
      "type": 0,
      "value": "Update"
    }
  ],
  "AgendaContribute.EventNew.create": [
    {
      "type": 0,
      "value": "Create the event"
    }
  ],
  "AgendaContribute.EventNew.deleteDraft": [
    {
      "type": 0,
      "value": "Delete the draft"
    }
  ],
  "AgendaContribute.EventNew.draft": [
    {
      "type": 0,
      "value": "Save as draft"
    }
  ],
  "AgendaContribute.EventNew.updateDraft": [
    {
      "type": 0,
      "value": "Update draft"
    }
  ],
  "AgendaContribute.Member.description": [
    {
      "type": 0,
      "value": "Su información personal sólo será visto por el equipo del agenda. Sólo el nombre de su organización será pública."
    }
  ],
  "AgendaContribute.Member.subtitle": [
    {
      "type": 0,
      "value": "Presentase antes de introducir sus eventos"
    }
  ],
  "AgendaContribute.Member.title": [
    {
      "type": 0,
      "value": "Bienvenido!"
    }
  ],
  "AgendaContribute.Stepper.confirmation": [
    {
      "type": 0,
      "value": "Confirmación"
    }
  ],
  "AgendaContribute.Stepper.event": [
    {
      "type": 0,
      "value": "Mi evento"
    }
  ],
  "AgendaContribute.Stepper.member": [
    {
      "type": 0,
      "value": "Perfil de miembro"
    }
  ]
}
